{
  "id_tmdb": "1924",
  "titulo": "Superman",
  "year": 1978,
  "imagen": "https://image.tmdb.org/t/p/w342/sYJGXqaDQzJ2qu2bhMDyTFtww7q.jpg",
  "type": "movie",
  "etiquetas": "Ciencia ficción, Acción, Aventura",
  "synopsis": "Desde una galaxia remota, un recién nacido es enviado por sus padres al espacio debido a la inminente destrucción del planeta donde viven. La nave aterriza en la Tierra, y el niño es adoptado por unos granjeros que le inculcan los mejores valores humanos. Con los años el joven se irá a Metrópolis y allí usará sus poderes sobrenaturales para luchar contra el mal.",
  "calidad": "HD",
  "enlaces": [
    {
      "nombre": "Enlace 1",
      "url": "https://yuguaab.com/e/yr2prk1wcslx",
      "type": "embed",
      "language": "Latino"
    },
    {
      "nombre": "Enlace 2",
      "url": "https://filemoon.sx/e/7j5s402o5bsr",
      "type": "embed",
      "language": "Latino"
    },
    {
      "nombre": "Enlace 3",
      "url": "https://yuguaab.com/e/mfauht4ayiwh",
      "type": "embed",
      "language": "Cast"
    },
    {
      "nombre": "Enlace 4",
      "url": "https://yuguaab.com/e/n7robzyax7kn",
      "type": "embed",
      "language": "Sub"
    }
  ],
  "updated_at": "2025-10-01T03:48:48.270Z",
  "temporadas": []
}