{
  "id_tmdb": "42413",
  "imagen": "https://image.tmdb.org/t/p/w342/39rU3RynR64KnM9sGCiz74fsdGn.jpg",
  "titulo": "Demon King Daimao",
  "año": "2010",
  "etiquetas": "Acción, Aventura, Animación, Comedia, Ciencia Ficción y Fantasía",
  "categorías": "Acción, Aventura, Animación, Comedia, Ciencia Ficción y Fantasía",
  "type": "animes",
  "created_at": "2010-04-03",
  "updated_at": "2025-09-09T05:41:26.834Z",
  "synopsis": "La historia se centra en Akuto Sai, que fue dejado recién nacido en los escalones de una iglesia por una bruja y bautizado como “Akuto”. Akuto Sai aspira en ser parte del orden más alto de magos en su país y contribuir a la sociedad como uno de sus clérigos. Un día es admitido en la Academia de Magia Constan, donde su prueba de aptitud predice lo siguiente: “Futura Ocupación…Rey demonio”. Así comienza su vida escolar en la que es odiado por la presidenta de su clase, perseguido por una chica con misteriosos poderes y custodiado por una hermosa androide.",
  "temporadas": [
    {
      "temporada": "Temporada 1",
      "capitulos": [
        {
          "episode_id": "1",
          "nombre": "1. Episodio 1",
          "portada": "https://image.tmdb.org/t/p/w300/eHApMoOgly4IIPpYYo2NjlwsLSd.jpg",
          "enlaces": [
            {
              "nombre": "Enlace 1",
              "url": "https://terabox.com/s/1LkYp-6BK4bYeQEPh_2JiKQ",
              "type": "embed",
              "language": "Sub"
            },
            {
              "nombre": "Enlace 2",
              "url": "https://fastream.to/embed-eacxzietoj98.html",
              "type": "embed",
              "language": "Sub"
            }
          ],
          "updated_at": "2025-09-09T05:41:26.834Z",
          "id": "880002"
        },
        {
          "episode_id": "2",
          "nombre": "2. Episodio 2",
          "portada": "https://image.tmdb.org/t/p/w300/guzOzBz4sZFfRjvf8rpt0QpWpew.jpg",
          "enlaces": [
            {
              "nombre": "Enlace 1",
              "url": "https://terabox.com/s/1WqNakThZrLhnWQiKaAtGAg",
              "type": "embed",
              "language": "Sub"
            },
            {
              "nombre": "Enlace 2",
              "url": "https://fastream.to/embed-pbithbcctp2p.html",
              "type": "embed",
              "language": "Sub"
            }
          ],
          "updated_at": "2025-09-09T05:41:26.834Z",
          "id": "880003"
        },
        {
          "episode_id": "3",
          "nombre": "3. Episodio 3",
          "portada": "https://image.tmdb.org/t/p/w300/cVE1xYi3Xc6lxJfoheikSrPL51z.jpg",
          "enlaces": [
            {
              "nombre": "Enlace 1",
              "url": "https://terabox.com/s/1S9X--0FjMxIzvPfttSPe9g",
              "type": "embed",
              "language": "Sub"
            },
            {
              "nombre": "Enlace 2",
              "url": "https://fastream.to/embed-uukxudjt19ui.html",
              "type": "embed",
              "language": "Sub"
            }
          ],
          "updated_at": "2025-09-09T05:41:26.834Z",
          "id": "880004"
        },
        {
          "episode_id": "4",
          "nombre": "4. Episodio 4",
          "portada": "https://image.tmdb.org/t/p/w300/rIL1nSRO50MxpYmvhrAMefToeTL.jpg",
          "enlaces": [
            {
              "nombre": "Enlace 1",
              "url": "https://terabox.com/s/1VaxfjYspUa2P0jJmugF8cg",
              "type": "embed",
              "language": "Sub"
            },
            {
              "nombre": "Enlace 2",
              "url": "https://fastream.to/embed-6ricg536zttj.html",
              "type": "embed",
              "language": "Sub"
            }
          ],
          "updated_at": "2025-09-09T05:41:26.834Z",
          "id": "880006"
        },
        {
          "episode_id": "5",
          "nombre": "5. Episodio 5",
          "portada": "https://image.tmdb.org/t/p/w300/oLAvoaW0DllARXJJyOPAPNnqZL4.jpg",
          "enlaces": [
            {
              "nombre": "Enlace 1",
              "url": "https://terabox.com/s/12Wk4G95X7Ng-7Qj5HCpahQ",
              "type": "embed",
              "language": "Sub"
            },
            {
              "nombre": "Enlace 2",
              "url": "https://fastream.to/embed-67oz293u874w.html",
              "type": "embed",
              "language": "Sub"
            }
          ],
          "updated_at": "2025-09-09T05:41:26.834Z",
          "id": "880005"
        },
        {
          "episode_id": "6",
          "nombre": "6. Episodio 6",
          "portada": "https://image.tmdb.org/t/p/w300/cYcA2VrWghIrWZ0xDf4M4lgmmxE.jpg",
          "enlaces": [
            {
              "nombre": "Enlace 1",
              "url": "https://terabox.com/s/1gna0jRuRy1TF8FgKw4ntNw",
              "type": "embed",
              "language": "Sub"
            },
            {
              "nombre": "Enlace 2",
              "url": "https://fastream.to/embed-ggi40jpzfgzl.html",
              "type": "embed",
              "language": "Sub"
            }
          ],
          "updated_at": "2025-09-09T05:41:26.834Z",
          "id": "880008"
        },
        {
          "episode_id": "7",
          "nombre": "7. Episodio 7",
          "portada": "https://image.tmdb.org/t/p/w300/5nbTJ7b4GoxJoj5BA9a6ZepUXmn.jpg",
          "enlaces": [
            {
              "nombre": "Enlace 1",
              "url": "https://terabox.com/s/1FRI82affCz_AeH6ILAr4-g",
              "type": "embed",
              "language": "Sub"
            },
            {
              "nombre": "Enlace 2",
              "url": "https://fastream.to/embed-m1lvtcudy2bo.html",
              "type": "embed",
              "language": "Sub"
            }
          ],
          "updated_at": "2025-09-09T05:41:26.834Z",
          "id": "880007"
        },
        {
          "episode_id": "8",
          "nombre": "8. Episodio 8",
          "portada": "https://image.tmdb.org/t/p/w300/rAKaiOCENFKTqZpBhrJqmASP4Gy.jpg",
          "enlaces": [
            {
              "nombre": "Enlace 1",
              "url": "https://terabox.com/s/18Yjsii-Zocz5avNPjW7G7w",
              "type": "embed",
              "language": "Sub"
            },
            {
              "nombre": "Enlace 2",
              "url": "https://fastream.to/embed-250oxfbtvb22.html",
              "type": "embed",
              "language": "Sub"
            }
          ],
          "updated_at": "2025-09-09T05:41:26.834Z",
          "id": "880009"
        },
        {
          "episode_id": "9",
          "nombre": "9. Episodio 9",
          "portada": "https://image.tmdb.org/t/p/w300/frjfh4R1ps9cBMJbLB9fLRQwxhw.jpg",
          "enlaces": [
            {
              "nombre": "Enlace 1",
              "url": "https://terabox.com/s/1-dLDIcPdiIgKSjCAQB83ww",
              "type": "embed",
              "language": "Sub"
            },
            {
              "nombre": "Enlace 2",
              "url": "https://fastream.to/embed-iw4docnqw8zl.html",
              "type": "embed",
              "language": "Sub"
            }
          ],
          "updated_at": "2025-09-09T05:41:26.834Z",
          "id": "880010"
        },
        {
          "episode_id": "10",
          "nombre": "10. Episodio 10",
          "portada": "https://image.tmdb.org/t/p/w300/fstU0l9r3mDImLT8O7AQNg3UDw3.jpg",
          "enlaces": [
            {
              "nombre": "Enlace 1",
              "url": "https://terabox.com/s/1LZEqpbarUbTXaY0JuT87_g",
              "type": "embed",
              "language": "Sub"
            },
            {
              "nombre": "Enlace 2",
              "url": "https://fastream.to/embed-c33ffsuzouts.html",
              "type": "embed",
              "language": "Sub"
            }
          ],
          "updated_at": "2025-09-09T05:41:26.834Z",
          "id": "880011"
        },
        {
          "episode_id": "11",
          "nombre": "11. Episodio 11",
          "portada": "https://image.tmdb.org/t/p/w300/7YKS6ydNCkdLmqU5Swebwj0GeqZ.jpg",
          "enlaces": [
            {
              "nombre": "Enlace 1",
              "url": "https://terabox.com/s/1iKr0n6VToR6FpOWptBB8jQ",
              "type": "embed",
              "language": "Sub"
            },
            {
              "nombre": "Enlace 2",
              "url": "https://fastream.to/embed-emaiuu5h42rc.html",
              "type": "embed",
              "language": "Sub"
            }
          ],
          "updated_at": "2025-09-09T05:41:26.834Z",
          "id": "880012"
        },
        {
          "episode_id": "12",
          "nombre": "12. Episodio 12",
          "portada": "https://image.tmdb.org/t/p/w300/vByCX9iEnbdpCeBZkv4KbbnVqLE.jpg",
          "enlaces": [
            {
              "nombre": "Enlace 1",
              "url": "https://terabox.com/s/11O_2MUt4DSpXOy2lAwmEiQ",
              "type": "embed",
              "language": "Sub"
            },
            {
              "nombre": "Enlace 2",
              "url": "https://fastream.to/embed-c3k9tt5r22qp.html",
              "type": "embed",
              "language": "Sub"
            }
          ],
          "updated_at": "2025-09-09T05:41:26.834Z",
          "id": "880013"
        }
      ]
    }
  ]
}