{
  "id_tmdb": "607",
  "titulo": "Hombres de negro",
  "year": 1997,
  "imagen": "https://image.tmdb.org/t/p/w342/gkcT1QmvspJ34rKgFUvv0ho0VrD.jpg",
  "type": "movie",
  "etiquetas": "Acción, Aventura, Comedia, Ciencia ficción",
  "synopsis": "Durante muchos años los extraterrestres han vivido en la Tierra, mezclados con los humanos, sin que nadie lo supiese. Los Hombres de Negro (Men in Black) son unos agentes, pertenecientes a una asociación altamente secreta del gobierno, encargados de controlar a los alienígenas. Ahora dos de estos agentes, uno veterano y otro recién incorporado, y que tienen como misión vigilar a los alienígenas que habitan en la ciudad de Nueva York, descubren a un terrorista galáctico que pretende acabar con la humanidad.",
  "calidad": "HD",
  "enlaces": [
    {
      "nombre": "Enlace 1",
      "url": "https://yuguaab.com/e/hn3o1eqn94na",
      "type": "embed",
      "language": "Latino"
    },
    {
      "nombre": "Enlace 2",
      "url": "https://filemoon.sx/e/e7x807qudg2d",
      "type": "embed",
      "language": "Latino"
    },
    {
      "nombre": "Enlace 3",
      "url": "https://yuguaab.com/e/nc443eyb67g0",
      "type": "embed",
      "language": "Cast"
    },
    {
      "nombre": "Enlace 4",
      "url": "https://yuguaab.com/e/819r1wbn9wd6",
      "type": "embed",
      "language": "Sub"
    }
  ],
  "updated_at": "2025-10-01T03:48:50.290Z",
  "temporadas": []
}