{
    "id_mal": "34497",
    "anime_id": "1244",
    "titulo": "Death March kara Hajimaru Isekai Kyousoukyoku",
    "titulo_original": "デスマーチからはじまる異世界狂想曲",
    "imagen": "https://myanimelist.net/images/anime/4/88911.jpg",
    "etiquetas": "Adventure, Fantasy",
    "year": "2018",
    "type": "anime",
    "synopsis": "Ichirou Suzuki, a programmer nearing his thirties, is drowning in work. Worn out, he eventually has a chance to catch up on sleep, only to wake up and discover himself in a fantasy RPG world, which is mashed together from the games he was debugging in reality. In this new place, he realizes that not only has his appearance changed to a younger version of himself, but his name has also changed to Satou, a nickname he used while running beta tests on games. \n\nHowever, before Satou can fully grasp his situation, an army of lizardmen launch an assault on him. Forced to cast a powerful spell in retaliation, Satou wipes them out completely and his level is boosted to 310, effectively maximizing his stats. Now, as a high-leveled adventurer armed with a plethora of skills and no way to return to reality, Satou sets out to explore this magical new world.\n\n[Written by MAL Rewrite]",
    "score": "6.4",
    "episodes": 12,
    "duration": "23 min per ep",
    "rating": "PG-13 - Teens 13 or older",
    "source": "Light novel",
    "status": "Currently Airing",
    "studios": [
        "SILVER LINK.",
        "Connect"
    ],
    "producers": [
        "Sotsu",
        "AT-X",
        "DIVE II Entertainment",
        "Tokyo MX",
        "Avex Pictures",
        "BS11",
        "Kadokawa",
        "KLab"
    ],
    "created_at": "2018-11-1",
    "updated_at": "2026-04-12T00:52:05.000Z",
    "player_base": [],
    "temporadas": [
        {
            "temporada": "Temporada 1",
            "capitulos": [
                {
                    "episode_id": "1",
                    "numero": 1,
                    "nombre": "Episodio 1",
                    "portada": "https://cdn.animeav1.com/screenshots/1244/1.jpg",
                    "enlaces": [
                        {
                            "nombre": "Server 1",
                            "url": "https://player.zilla-networks.com/play/d9966c676fbdbc2dd369ec989b879fb5",
                            "type": "embed",
                            "language": "Sub"
                        },
                        {
                            "nombre": "Server 2",
                            "url": "https://player.zilla-networks.com/m3u8/d9966c676fbdbc2dd369ec989b879fb5",
                            "type": "mp4",
                            "language": "Sub"
                        }
                    ]
                },
                {
                    "episode_id": "2",
                    "numero": 2,
                    "nombre": "Episodio 2",
                    "portada": "https://cdn.animeav1.com/screenshots/1244/2.jpg",
                    "enlaces": [
                        {
                            "nombre": "Server 1",
                            "url": "https://player.zilla-networks.com/play/30dddd9aae64e689870a28cad310c0c2",
                            "type": "embed",
                            "language": "Sub"
                        },
                        {
                            "nombre": "Server 2",
                            "url": "https://player.zilla-networks.com/m3u8/30dddd9aae64e689870a28cad310c0c2",
                            "type": "mp4",
                            "language": "Sub"
                        }
                    ]
                },
                {
                    "episode_id": "3",
                    "numero": 3,
                    "nombre": "Episodio 3",
                    "portada": "https://cdn.animeav1.com/screenshots/1244/3.jpg",
                    "enlaces": [
                        {
                            "nombre": "Server 1",
                            "url": "https://player.zilla-networks.com/play/8535e8473998cf9250cac5216767dcf7",
                            "type": "embed",
                            "language": "Sub"
                        },
                        {
                            "nombre": "Server 2",
                            "url": "https://player.zilla-networks.com/m3u8/8535e8473998cf9250cac5216767dcf7",
                            "type": "mp4",
                            "language": "Sub"
                        }
                    ]
                },
                {
                    "episode_id": "4",
                    "numero": 4,
                    "nombre": "Episodio 4",
                    "portada": "https://cdn.animeav1.com/screenshots/1244/4.jpg",
                    "enlaces": [
                        {
                            "nombre": "Server 1",
                            "url": "https://player.zilla-networks.com/play/236e220683b6f4e1622295a5b74a8563",
                            "type": "embed",
                            "language": "Sub"
                        },
                        {
                            "nombre": "Server 2",
                            "url": "https://player.zilla-networks.com/m3u8/236e220683b6f4e1622295a5b74a8563",
                            "type": "mp4",
                            "language": "Sub"
                        }
                    ]
                },
                {
                    "episode_id": "5",
                    "numero": 5,
                    "nombre": "Episodio 5",
                    "portada": "https://cdn.animeav1.com/screenshots/1244/5.jpg",
                    "enlaces": [
                        {
                            "nombre": "Server 1",
                            "url": "https://player.zilla-networks.com/play/cf7812400e580e0285a1873d935d4079",
                            "type": "embed",
                            "language": "Sub"
                        },
                        {
                            "nombre": "Server 2",
                            "url": "https://player.zilla-networks.com/m3u8/cf7812400e580e0285a1873d935d4079",
                            "type": "mp4",
                            "language": "Sub"
                        }
                    ]
                },
                {
                    "episode_id": "6",
                    "numero": 6,
                    "nombre": "Episodio 6",
                    "portada": "https://cdn.animeav1.com/screenshots/1244/6.jpg",
                    "enlaces": [
                        {
                            "nombre": "Server 1",
                            "url": "https://player.zilla-networks.com/play/fb0cfc64f109176c0b9dd1c296c22c32",
                            "type": "embed",
                            "language": "Sub"
                        },
                        {
                            "nombre": "Server 2",
                            "url": "https://player.zilla-networks.com/m3u8/fb0cfc64f109176c0b9dd1c296c22c32",
                            "type": "mp4",
                            "language": "Sub"
                        }
                    ]
                },
                {
                    "episode_id": "7",
                    "numero": 7,
                    "nombre": "Episodio 7",
                    "portada": "https://cdn.animeav1.com/screenshots/1244/7.jpg",
                    "enlaces": [
                        {
                            "nombre": "Server 1",
                            "url": "https://player.zilla-networks.com/play/4ea7059e390a4f93977e1e0872d96f6a",
                            "type": "embed",
                            "language": "Sub"
                        },
                        {
                            "nombre": "Server 2",
                            "url": "https://player.zilla-networks.com/m3u8/4ea7059e390a4f93977e1e0872d96f6a",
                            "type": "mp4",
                            "language": "Sub"
                        }
                    ]
                },
                {
                    "episode_id": "8",
                    "numero": 8,
                    "nombre": "Episodio 8",
                    "portada": "https://cdn.animeav1.com/screenshots/1244/8.jpg",
                    "enlaces": [
                        {
                            "nombre": "Server 1",
                            "url": "https://player.zilla-networks.com/play/8c99e705bbcd43b65c1d0ee6c8bf47ca",
                            "type": "embed",
                            "language": "Sub"
                        },
                        {
                            "nombre": "Server 2",
                            "url": "https://player.zilla-networks.com/m3u8/8c99e705bbcd43b65c1d0ee6c8bf47ca",
                            "type": "mp4",
                            "language": "Sub"
                        }
                    ]
                },
                {
                    "episode_id": "9",
                    "numero": 9,
                    "nombre": "Episodio 9",
                    "portada": "https://cdn.animeav1.com/screenshots/1244/9.jpg",
                    "enlaces": [
                        {
                            "nombre": "Server 1",
                            "url": "https://player.zilla-networks.com/play/d5edefc7223ecaf54982ad9bf7190d9c",
                            "type": "embed",
                            "language": "Sub"
                        },
                        {
                            "nombre": "Server 2",
                            "url": "https://player.zilla-networks.com/m3u8/d5edefc7223ecaf54982ad9bf7190d9c",
                            "type": "mp4",
                            "language": "Sub"
                        }
                    ]
                },
                {
                    "episode_id": "10",
                    "numero": 10,
                    "nombre": "Episodio 10",
                    "portada": "https://cdn.animeav1.com/screenshots/1244/10.jpg",
                    "enlaces": [
                        {
                            "nombre": "Server 1",
                            "url": "https://player.zilla-networks.com/play/662e0afd88664fe5ded7bf3c5388ad44",
                            "type": "embed",
                            "language": "Sub"
                        },
                        {
                            "nombre": "Server 2",
                            "url": "https://player.zilla-networks.com/m3u8/662e0afd88664fe5ded7bf3c5388ad44",
                            "type": "mp4",
                            "language": "Sub"
                        }
                    ]
                },
                {
                    "episode_id": "11",
                    "numero": 11,
                    "nombre": "Episodio 11",
                    "portada": "https://cdn.animeav1.com/screenshots/1244/11.jpg",
                    "enlaces": [
                        {
                            "nombre": "Server 1",
                            "url": "https://player.zilla-networks.com/play/3fb6390ff9af4338b355901da9405b34",
                            "type": "embed",
                            "language": "Sub"
                        },
                        {
                            "nombre": "Server 2",
                            "url": "https://player.zilla-networks.com/m3u8/3fb6390ff9af4338b355901da9405b34",
                            "type": "mp4",
                            "language": "Sub"
                        }
                    ]
                },
                {
                    "episode_id": "12",
                    "numero": 12,
                    "nombre": "Episodio 12",
                    "portada": "https://cdn.animeav1.com/screenshots/1244/12.jpg",
                    "enlaces": [
                        {
                            "nombre": "Server 1",
                            "url": "https://player.zilla-networks.com/play/78a8a05f3e16446d411dcc0816db1987",
                            "type": "embed",
                            "language": "Sub"
                        },
                        {
                            "nombre": "Server 2",
                            "url": "https://player.zilla-networks.com/m3u8/78a8a05f3e16446d411dcc0816db1987",
                            "type": "mp4",
                            "language": "Sub"
                        }
                    ]
                }
            ]
        }
    ]
}