{
    "id_mal": "61067",
    "titulo": "Ninja to Gokudou",
    "titulo_original": "忍者と極道",
    "imagen": "https:\/\/myanimelist.net\/images\/anime\/1296\/152147l.jpg",
    "etiquetas": "Action",
    "year": "2025",
    "type": "anime",
    "synopsis": "Since ancient times, the ninja and the yakuza have been at war, spilling blood around the world as empires rise and fall. So when, in the modern age, Shinoha, a ninja, meets Kiwami, a gangster following the path of the yakuza—the gokudo—and discovers they have common interests, the obvious assumption is that nothing good can come of it. But can it be that one burgeoning bromance will shake up a 300-year grudge?\n\nWho will win the struggle for real ultimate power?\n\n(Source: Kodansha USA)",
    "score": "6.4",
    "episodes": 12,
    "duration": "23 min per ep",
    "rating": "R - 17+ (violence & profanity)",
    "source": "Web manga",
    "status": "Finished Airing",
    "studios": [
        "Studio Deen"
    ],
    "producers": [
        "Kodansha",
        "Magic Capsule",
        "Nippon Television Network",
        "Nippon Television Music",
        "Good Smile Film",
        "NK Animation"
    ],
    "created_at": "2025-10-08",
    "updated_at": "2026-03-18T10:49:50.000Z",
    "player_base": [],
    "temporadas": [
        {
            "temporada": "Temporada 1",
            "capitulos": [
                {
                    "episode_id": "01",
                    "numero": 1,
                    "nombre": "01. Episodio 1",
                    "portada": "",
                    "enlaces": [
                        {
                            "nombre": "Enlace 1",
                            "url": "https:\/\/player.zilla-networks.com\/play\/133f6d525f7a9450947385198dc254e2",
                            "type": "embed",
                            "language": "Latino"
                        },
                        {
                            "nombre": "Enlace 2",
                            "url": "https:\/\/player.zilla-networks.com\/m3u8\/133f6d525f7a9450947385198dc254e2",
                            "type": "mp4",
                            "language": "Latino"
                        },
                        {
                            "nombre": "Enlace 3",
                            "url": "https:\/\/player.zilla-networks.com\/play\/799fca8a9fbc9ed00a007901cbef2571",
                            "type": "embed",
                            "language": "Sub"
                        },
                        {
                            "nombre": "Enlace 4",
                            "url": "https:\/\/player.zilla-networks.com\/m3u8\/799fca8a9fbc9ed00a007901cbef2571",
                            "type": "mp4",
                            "language": "Sub"
                        }
                    ]
                },
                {
                    "episode_id": "02",
                    "numero": 2,
                    "nombre": "02. Episodio 2",
                    "portada": "",
                    "enlaces": [
                        {
                            "nombre": "Enlace 1",
                            "url": "https:\/\/player.zilla-networks.com\/play\/e01431cff1d3eb558feee33d02b9efa8",
                            "type": "embed",
                            "language": "Latino"
                        },
                        {
                            "nombre": "Enlace 2",
                            "url": "https:\/\/player.zilla-networks.com\/m3u8\/e01431cff1d3eb558feee33d02b9efa8",
                            "type": "mp4",
                            "language": "Latino"
                        },
                        {
                            "nombre": "Enlace 3",
                            "url": "https:\/\/player.zilla-networks.com\/play\/66e3c7fc233731471b75da04a2d7c880",
                            "type": "embed",
                            "language": "Sub"
                        },
                        {
                            "nombre": "Enlace 4",
                            "url": "https:\/\/player.zilla-networks.com\/m3u8\/66e3c7fc233731471b75da04a2d7c880",
                            "type": "mp4",
                            "language": "Sub"
                        }
                    ]
                },
                {
                    "episode_id": "03",
                    "numero": 3,
                    "nombre": "03. Episodio 3",
                    "portada": "",
                    "enlaces": [
                        {
                            "nombre": "Enlace 1",
                            "url": "https:\/\/player.zilla-networks.com\/play\/2e4473d7ca00942a83b1dd7ca3eae319",
                            "type": "embed",
                            "language": "Latino"
                        },
                        {
                            "nombre": "Enlace 2",
                            "url": "https:\/\/player.zilla-networks.com\/m3u8\/2e4473d7ca00942a83b1dd7ca3eae319",
                            "type": "mp4",
                            "language": "Latino"
                        },
                        {
                            "nombre": "Enlace 3",
                            "url": "https:\/\/player.zilla-networks.com\/play\/c8f003c57c04b569e3f7ddb4851724c9",
                            "type": "embed",
                            "language": "Sub"
                        },
                        {
                            "nombre": "Enlace 4",
                            "url": "https:\/\/player.zilla-networks.com\/m3u8\/c8f003c57c04b569e3f7ddb4851724c9",
                            "type": "mp4",
                            "language": "Sub"
                        }
                    ]
                },
                {
                    "episode_id": "04",
                    "numero": 4,
                    "nombre": "04. Episodio 4",
                    "portada": "",
                    "enlaces": [
                        {
                            "nombre": "Enlace 1",
                            "url": "https:\/\/player.zilla-networks.com\/play\/2825c03e5dd800bd39fddcd5c6fa6bcb",
                            "type": "embed",
                            "language": "Latino"
                        },
                        {
                            "nombre": "Enlace 2",
                            "url": "https:\/\/player.zilla-networks.com\/m3u8\/2825c03e5dd800bd39fddcd5c6fa6bcb",
                            "type": "mp4",
                            "language": "Latino"
                        },
                        {
                            "nombre": "Enlace 3",
                            "url": "https:\/\/player.zilla-networks.com\/play\/dc294ef77ac5bb8a297b70373278039d",
                            "type": "embed",
                            "language": "Sub"
                        },
                        {
                            "nombre": "Enlace 4",
                            "url": "https:\/\/player.zilla-networks.com\/m3u8\/dc294ef77ac5bb8a297b70373278039d",
                            "type": "mp4",
                            "language": "Sub"
                        }
                    ]
                },
                {
                    "episode_id": "05",
                    "numero": 5,
                    "nombre": "05. Episodio 5",
                    "portada": "",
                    "enlaces": [
                        {
                            "nombre": "Enlace 1",
                            "url": "https:\/\/player.zilla-networks.com\/play\/bdc19350f506cf389e433bd92eeeb7a9",
                            "type": "embed",
                            "language": "Latino"
                        },
                        {
                            "nombre": "Enlace 2",
                            "url": "https:\/\/player.zilla-networks.com\/m3u8\/bdc19350f506cf389e433bd92eeeb7a9",
                            "type": "mp4",
                            "language": "Latino"
                        },
                        {
                            "nombre": "Enlace 3",
                            "url": "https:\/\/player.zilla-networks.com\/play\/c66dc1238d4d4979edefbbd073393121",
                            "type": "embed",
                            "language": "Sub"
                        },
                        {
                            "nombre": "Enlace 4",
                            "url": "https:\/\/player.zilla-networks.com\/m3u8\/c66dc1238d4d4979edefbbd073393121",
                            "type": "mp4",
                            "language": "Sub"
                        }
                    ]
                },
                {
                    "episode_id": "06",
                    "numero": 6,
                    "nombre": "06. Episodio 6",
                    "portada": "",
                    "enlaces": [
                        {
                            "nombre": "Enlace 1",
                            "url": "https:\/\/player.zilla-networks.com\/play\/818450b0991bb075893fb8e3ec27debe",
                            "type": "embed",
                            "language": "Latino"
                        },
                        {
                            "nombre": "Enlace 2",
                            "url": "https:\/\/player.zilla-networks.com\/m3u8\/818450b0991bb075893fb8e3ec27debe",
                            "type": "mp4",
                            "language": "Latino"
                        },
                        {
                            "nombre": "Enlace 3",
                            "url": "https:\/\/player.zilla-networks.com\/play\/88e4580e250522b80016cb3e7ee8dcee",
                            "type": "embed",
                            "language": "Sub"
                        },
                        {
                            "nombre": "Enlace 4",
                            "url": "https:\/\/player.zilla-networks.com\/m3u8\/88e4580e250522b80016cb3e7ee8dcee",
                            "type": "mp4",
                            "language": "Sub"
                        }
                    ]
                },
                {
                    "episode_id": "07",
                    "numero": 7,
                    "nombre": "07. Episodio 7",
                    "portada": "",
                    "enlaces": [
                        {
                            "nombre": "Enlace 1",
                            "url": "https:\/\/player.zilla-networks.com\/play\/dac469d8706f96d55fd7d80b81723a1e",
                            "type": "embed",
                            "language": "Latino"
                        },
                        {
                            "nombre": "Enlace 2",
                            "url": "https:\/\/player.zilla-networks.com\/m3u8\/dac469d8706f96d55fd7d80b81723a1e",
                            "type": "mp4",
                            "language": "Latino"
                        },
                        {
                            "nombre": "Enlace 3",
                            "url": "https:\/\/player.zilla-networks.com\/play\/e66c77b7966fd9da4fe9c2fe1459696f",
                            "type": "embed",
                            "language": "Sub"
                        },
                        {
                            "nombre": "Enlace 4",
                            "url": "https:\/\/player.zilla-networks.com\/m3u8\/e66c77b7966fd9da4fe9c2fe1459696f",
                            "type": "mp4",
                            "language": "Sub"
                        }
                    ]
                },
                {
                    "episode_id": "08",
                    "numero": 8,
                    "nombre": "08. Episodio 8",
                    "portada": "",
                    "enlaces": [
                        {
                            "nombre": "Enlace 1",
                            "url": "https:\/\/player.zilla-networks.com\/play\/7d43291e1aacb3b22c59831cb4395c7f",
                            "type": "embed",
                            "language": "Latino"
                        },
                        {
                            "nombre": "Enlace 2",
                            "url": "https:\/\/player.zilla-networks.com\/m3u8\/7d43291e1aacb3b22c59831cb4395c7f",
                            "type": "mp4",
                            "language": "Latino"
                        },
                        {
                            "nombre": "Enlace 3",
                            "url": "https:\/\/player.zilla-networks.com\/play\/427599d6d503f80d6fad1c3b1209b687",
                            "type": "embed",
                            "language": "Sub"
                        },
                        {
                            "nombre": "Enlace 4",
                            "url": "https:\/\/player.zilla-networks.com\/m3u8\/427599d6d503f80d6fad1c3b1209b687",
                            "type": "mp4",
                            "language": "Sub"
                        }
                    ]
                },
                {
                    "episode_id": "09",
                    "numero": 9,
                    "nombre": "09. Episodio 9",
                    "portada": "",
                    "enlaces": [
                        {
                            "nombre": "Enlace 1",
                            "url": "https:\/\/player.zilla-networks.com\/play\/355329da1eeedbb7f2ed455922c38813",
                            "type": "embed",
                            "language": "Latino"
                        },
                        {
                            "nombre": "Enlace 2",
                            "url": "https:\/\/player.zilla-networks.com\/m3u8\/355329da1eeedbb7f2ed455922c38813",
                            "type": "mp4",
                            "language": "Latino"
                        },
                        {
                            "nombre": "Enlace 3",
                            "url": "https:\/\/player.zilla-networks.com\/play\/a99fb0811774d9fceddb114700bde1da",
                            "type": "embed",
                            "language": "Sub"
                        },
                        {
                            "nombre": "Enlace 4",
                            "url": "https:\/\/player.zilla-networks.com\/m3u8\/a99fb0811774d9fceddb114700bde1da",
                            "type": "mp4",
                            "language": "Sub"
                        }
                    ]
                },
                {
                    "episode_id": "10",
                    "numero": 10,
                    "nombre": "10. Episodio 10",
                    "portada": "",
                    "enlaces": [
                        {
                            "nombre": "Enlace 1",
                            "url": "https:\/\/player.zilla-networks.com\/play\/dca423ada68abfc138ff4722ef68936b",
                            "type": "embed",
                            "language": "Latino"
                        },
                        {
                            "nombre": "Enlace 2",
                            "url": "https:\/\/player.zilla-networks.com\/m3u8\/dca423ada68abfc138ff4722ef68936b",
                            "type": "mp4",
                            "language": "Latino"
                        },
                        {
                            "nombre": "Enlace 3",
                            "url": "https:\/\/player.zilla-networks.com\/play\/81df97cbe4cc21765e50adf92b0af476",
                            "type": "embed",
                            "language": "Sub"
                        },
                        {
                            "nombre": "Enlace 4",
                            "url": "https:\/\/player.zilla-networks.com\/m3u8\/81df97cbe4cc21765e50adf92b0af476",
                            "type": "mp4",
                            "language": "Sub"
                        }
                    ]
                },
                {
                    "episode_id": "11",
                    "numero": 11,
                    "nombre": "11. Episodio 11",
                    "portada": "",
                    "enlaces": [
                        {
                            "nombre": "Enlace 1",
                            "url": "https:\/\/player.zilla-networks.com\/play\/f61678c89e201a5216c23bf83f2b2d24",
                            "type": "embed",
                            "language": "Latino"
                        },
                        {
                            "nombre": "Enlace 2",
                            "url": "https:\/\/player.zilla-networks.com\/m3u8\/f61678c89e201a5216c23bf83f2b2d24",
                            "type": "mp4",
                            "language": "Latino"
                        },
                        {
                            "nombre": "Enlace 3",
                            "url": "https:\/\/player.zilla-networks.com\/play\/89d440f604a699a046b7084d21093c70",
                            "type": "embed",
                            "language": "Sub"
                        },
                        {
                            "nombre": "Enlace 4",
                            "url": "https:\/\/player.zilla-networks.com\/m3u8\/89d440f604a699a046b7084d21093c70",
                            "type": "mp4",
                            "language": "Sub"
                        }
                    ]
                },
                {
                    "episode_id": "12",
                    "numero": 12,
                    "nombre": "12. Episodio 12",
                    "portada": "",
                    "enlaces": [
                        {
                            "nombre": "Enlace 1",
                            "url": "https:\/\/player.zilla-networks.com\/play\/148b5bfe75315a5180441109cc5fd202",
                            "type": "embed",
                            "language": "Latino"
                        },
                        {
                            "nombre": "Enlace 2",
                            "url": "https:\/\/player.zilla-networks.com\/m3u8\/148b5bfe75315a5180441109cc5fd202",
                            "type": "mp4",
                            "language": "Latino"
                        },
                        {
                            "nombre": "Enlace 3",
                            "url": "https:\/\/player.zilla-networks.com\/play\/96209e4ba01701e771a21b41c6256405",
                            "type": "embed",
                            "language": "Sub"
                        },
                        {
                            "nombre": "Enlace 4",
                            "url": "https:\/\/player.zilla-networks.com\/m3u8\/96209e4ba01701e771a21b41c6256405",
                            "type": "mp4",
                            "language": "Sub"
                        }
                    ]
                }
            ]
        }
    ]
}